MANIFEST.in
l10n_in_hr_payroll_demo.xml
l10n_in_hr_payroll_report.xml
l10n_in_hr_payroll_sequence.xml
l10n_in_hr_payroll_view.xml
setup.py
./__init__.py
./__openerp__.py
./l10n_in_hr_payroll.py
./report/__init__.py
./report/payment_advice_report.py
./report/payslip_report.py
./report/report_hr_salary_employee_bymonth.py
./report/report_hr_yearly_salary_detail.py
./report/report_payroll_advice.py
./report/report_payslip_details.py
./wizard/__init__.py
./wizard/hr_salary_employee_bymonth.py
./wizard/hr_yearly_salary_detail.py
data/hr.salary.rule.csv
data/l10n_in_hr_payroll_data.xml
i18n/bn.po
i18n/es.po
i18n/gu.po
i18n/hi.po
i18n/l10n_in_hr_payroll.pot
i18n/nl.po
i18n/pl.po
i18n/pt.po
i18n/pt_BR.po
i18n/sl.po
i18n/ta.po
i18n/te.po
i18n/tr.po
i18n/zh_CN.po
openerp_l10n_in_hr_payroll.egg-info/PKG-INFO
openerp_l10n_in_hr_payroll.egg-info/SOURCES.txt
openerp_l10n_in_hr_payroll.egg-info/dependency_links.txt
openerp_l10n_in_hr_payroll.egg-info/requires.txt
openerp_l10n_in_hr_payroll.egg-info/top_level.txt
report/payment_advice_report_view.xml
report/payslip_report_view.xml
report/report_hr_salary_employee_bymonth.rml
report/report_hr_salary_employee_bymonth.sxw
report/report_hr_yearly_salary_detail.rml
report/report_hr_yearly_salary_detail.sxw
report/report_payroll_advice.rml
report/report_payroll_advice.sxw
report/report_payslip_details.rml
report/report_payslip_details.sxw
security/ir.model.access.csv
static/src/img/icon.png
test/payment_advice.yml
test/payment_advice_batch.yml
wizard/hr_salary_employee_bymonth_view.xml
wizard/hr_yearly_salary_detail_view.xml